LICENSE
MANIFEST.in
README.md
VERSION
example_env.cfg
setup.cfg
setup.py
src/PlantStation/App.py
src/PlantStation/Configure.py
src/PlantStation/Environment.py
src/PlantStation/Plant.py
src/PlantStation/__init__.py
src/PlantStation/__main__.py
src/PlantStation.egg-info/PKG-INFO
src/PlantStation.egg-info/SOURCES.txt
src/PlantStation.egg-info/dependency_links.txt
src/PlantStation.egg-info/entry_points.txt
src/PlantStation.egg-info/not-zip-safe
src/PlantStation.egg-info/requires.txt
src/PlantStation.egg-info/top_level.txt
src/PlantStation/helpers/__init__.py
src/PlantStation/helpers/format_validators.py
src/PlantStation/helpers/sched_states.py