Metadata-Version: 2.1
Name: PlantStation
Version: 0.1.1rc0
Summary: A little daemon to keep plants watered with Raspberry Pi
Home-page: https://github.com/j-kk/PlantStation/
Author: Jakub Kowalski
Author-email: k_jakub@icloud.com
License: UNKNOWN
Platform: UNKNOWN
Classifier: License :: OSI Approved :: MIT License
Classifier: Programming Language :: Python
Classifier: Programming Language :: Python :: 3 :: Only
Classifier: Programming Language :: Python :: 3.6
Classifier: Programming Language :: Python :: 3.7
Classifier: Programming Language :: Python :: 3.8
Classifier: Development Status :: 4 - Beta
Classifier: Environment :: No Input/Output (Daemon)
Classifier: Environment :: Console
Requires-Python: >=3.6
Provides-Extra: testing
Provides-Extra: docs
